MANIFEST.in
VERSION
setup.py
tensorshield.ext.api.egg-info/PKG-INFO
tensorshield.ext.api.egg-info/SOURCES.txt
tensorshield.ext.api.egg-info/dependency_links.txt
tensorshield.ext.api.egg-info/requires.txt
tensorshield.ext.api.egg-info/top_level.txt
tensorshield/ext/api/__init__.py
tensorshield/ext/api/_client.py
tensorshield/ext/api/_requestmodel.py
tensorshield/ext/api/_responsemodel.py
tensorshield/ext/api/_rootresponsemodel.py
tensorshield/ext/api/package.json
tensorshield/ext/api/models/__init__.py
tensorshield/ext/api/models/_messagecodechallengeanswer.py
tensorshield/ext/api/models/_openauthorizationchallengemethod.py
tensorshield/ext/api/models/_principalchallengemethod.py
tensorshield/ext/api/models/_verificationcodechallengemethod.py
tensorshield/ext/api/v1/__init__.py
tensorshield/ext/api/v1/_annotations.py
tensorshield/ext/api/v1/_principalchallengerequest.py
tensorshield/ext/api/v1/_principalchallengeresponse.py
tensorshield/ext/api/v1/_principalsolverequest.py
tensorshield/ext/api/v1/_principalsolveresponse.py
tensorshield/ext/api/v1/_principalverificationrequest.py
tensorshield/ext/api/v1/_principalverificationresponse.py
tensorshield/ext/api/v1/_requestmodel.py